[{"id":1,"name":"Analise Windsor","email":"Analise_Windsor3841@cispeto.com","address":"Biggerstaff   Alley, 9752"},{"id":2,"name":"Marina Blythe","email":"Marina_Blythe3933@womeona.net","address":"Bingham   Hill, 6146"},{"id":3,"name":"Ramon Stuart","email":"Ramon_Stuart7325@hourpy.biz","address":"Thoresby   Boulevard, 7091"},{"id":4,"name":"Chris Kaur","email":"Chris_Kaur1584@famism.biz","address":"Ashley Way, 3566"},{"id":5,"name":"Denis York","email":"Denis_York870@vetan.org","address":"Angel  Avenue, 2093"},{"id":6,"name":"Isla Hall","email":"Isla_Hall6111@cispeto.com","address":"Camden  Walk, 6609"},{"id":7,"name":"Stacy Logan","email":"Stacy_Logan837@guentu.biz","address":"Bermondsey    Crossroad, 5237"},{"id":8,"name":"Anabel Norton","email":"Anabel_Norton274@bauros.biz","address":"Thoresby   Lane, 8708"},{"id":9,"name":"Cristal Welsch","email":"Cristal_Welsch6802@jiman.org","address":"Lake Drive, 3925"}]